CHANGES.txt
CONTRIBUTING.md
MANIFEST.in
README.md
logo.png
setup.py
clippercard/__init__.py
clippercard/client.py
clippercard/main.py
clippercard/parser.py
clippercard/porcelain.py
clippercard.egg-info/PKG-INFO
clippercard.egg-info/SOURCES.txt
clippercard.egg-info/dependency_links.txt
clippercard.egg-info/entry_points.txt
clippercard.egg-info/requires.txt
clippercard.egg-info/top_level.txt
tests/test_parsing.py