Metadata-Version: 2.1
Name: clippercard
Version: 202104.25.1
Summary: Unofficial Python API for Clipper Card (transportation pass used in the SF Bay Area)
Home-page: https://github.com/clippercard/clippercard-python
Author: Your friendly neighborhood transit rider-hackers
Author-email: goldengate88@systemfu.com
License: MIT
Platform: UNKNOWN
Classifier: Intended Audience :: Developers
Classifier: License :: OSI Approved :: MIT License
Classifier: Programming Language :: Python
Classifier: Programming Language :: Python :: 3.6
Classifier: Programming Language :: Python :: 3.7
Classifier: Programming Language :: Python :: 3.8
Classifier: Programming Language :: Python :: 3.9
Classifier: Programming Language :: Python :: 3.10
Classifier: Programming Language :: Python :: 3 :: Only
Classifier: Topic :: Software Development :: Libraries :: Python Modules
Requires-Python: >=3.6
